nicegui_cocircular/__init__.py
nicegui_cocircular/cocircular.py
nicegui_cocircular/feature.py
nicegui_cocircular/py.typed
nicegui_cocircular-0.1.0.dist-info/METADATA
nicegui_cocircular-0.1.0.dist-info/WHEEL
nicegui_cocircular-0.1.0.dist-info/entry_points.txt
nicegui_cocircular-0.1.0.dist-info/RECORD
