Metadata-Version: 2.4
Name: nicegui-cocircular
Version: 0.1.0
Summary: CoCircular
Project-URL: homepage, https://github.com/SaitoTsutomu/nicegui-cocircular
Author-email: Saito Tsutomu <tsutomu.saito@moai-lab.jp>
Classifier: Development Status :: 1 - Planning
Classifier: License :: OSI Approved :: Apache Software License
Classifier: Programming Language :: Python
Classifier: Topic :: Scientific/Engineering
Classifier: Topic :: Software Development
Requires-Python: >=3.13
Requires-Dist: fire>=0.7.0
Requires-Dist: nicegui>=2.20.0
Requires-Dist: numpy>=2.3.1
